readability/__init__.py
readability/browser.py
readability/cleaners.py
readability/compat/__init__.py
readability/compat/three.py
readability/compat/two.py
readability/debug.py
readability/encoding.py
readability/htmls.py
readability/readability.py
r2k/__init__.py
r2k/cli/__init__.py
r2k/cli/cli_utils.py
r2k/cli/config/__init__.py
r2k/cli/config/config_init.py
r2k/cli/config/config_set.py
r2k/cli/config/config_show.py
r2k/cli/config/prompts.py
r2k/cli/feed/__init__.py
r2k/cli/feed/feed_add.py
r2k/cli/feed/feed_import.py
r2k/cli/feed/feed_remove.py
r2k/cli/feed/feed_show.py
r2k/cli/kindle/__init__.py
r2k/cli/kindle/kindle_send.py
r2k/cli/logger.py
r2k/config.py
r2k/constants.py
r2k/dates.py
r2k/ebook/__init__.py
r2k/ebook/base_parser.py
r2k/ebook/epub_builder.py
r2k/ebook/images.py
r2k/ebook/mercury_parser.py
r2k/ebook/readability_parser.py
r2k/ebook/single_article.py
r2k/email_sender.py
r2k/feeds.py
r2k/gmail/__init__.py
r2k/unicode.py
templates/article.html
templates/epub/META-INF/container.xml
templates/epub/OEBPS/content/article.xhtml
templates/epub/OEBPS/content.opf
templates/epub/OEBPS/images/cover.png
templates/epub/OEBPS/stylesheet.css
templates/epub/OEBPS/title.xhtml
templates/epub/OEBPS/toc.ncx
templates/epub/OEBPS/toc.xhtml
templates/epub/_r2k/navpoint.xml
templates/epub/mimetype
templates/main.html
templates/toc.html
r2k-0.7.4.dist-info/entry_points.txt
r2k-0.7.4.dist-info/LICENSE
r2k-0.7.4.dist-info/WHEEL
r2k-0.7.4.dist-info/METADATA
r2k-0.7.4.dist-info/RECORD
