Metadata-Version: 2.1
Name: r2k
Version: 0.7.4
Summary: A tool that lets you periodically send articles received from an RSS feed to your Kindle
Home-page: https://github.com/mcouthon/r2k
License: MIT
Keywords: rss,atom,kindle,reading
Author: Pavel Brodsky
Author-email: mcouthon@gmail.com
Requires-Python: >=3.8,<4.0
Classifier: License :: OSI Approved :: MIT License
Classifier: Programming Language :: Python :: 3
Classifier: Programming Language :: Python :: 3.10
Classifier: Programming Language :: Python :: 3.8
Classifier: Programming Language :: Python :: 3.9
Provides-Extra: docker
Requires-Dist: arrow (>=0.15.8,<0.16.0)
Requires-Dist: beautifulsoup4 (>=4.9.0,<5.0.0)
Requires-Dist: chardet (>=3.0.4,<4.0.0)
Requires-Dist: click (>=7.1.1,<8.0.0)
Requires-Dist: cssselect (>=1.1.0,<2.0.0)
Requires-Dist: docker (>=4.2.0,<5.0.0); extra == "docker"
Requires-Dist: feedparser (>=5.2.1,<6.0.0)
Requires-Dist: lxml (>=4.5.2,<5.0.0)
Requires-Dist: orjson (>=3.6.7,<4.0.0)
Requires-Dist: pick (>=0.6.7,<0.7.0)
Requires-Dist: python-dateutil (>=2.8.1,<3.0.0)
Requires-Dist: pyyaml (>=5.3.1,<6.0.0)
Requires-Dist: requests (>=2.24.0,<3.0.0)
Project-URL: Repository, https://github.com/mcouthon/r2k
